{
  "UsuarioActivo": [
    {
      "id": "2323",
      "nombreUsuario": "lucas"
    }
  ],
  "Usuarios": [
    {
      "id": "2323",
      "nombreUsuario": "lucas",
      "contrasena": "123123",
      "email": "Lucassmartin.costa@gmail.com",
      "listas": [
        {
          "id": 8,
          "nombre": "laura",
          "recetas": []
        },
        {
          "id": 11,
          "nombre": "laura",
          "recetas": []
        },
        {
          "id": 13,
          "nombre": "laura",
          "recetas": []
        },
        {
          "id": 14,
          "nombre": "laura",
          "recetas": []
        },
        {
          "id": 8,
          "nombre": "mediterraneo",
          "recetas": []
        },
        {
          "id": 9,
          "nombre": "prueba 2",
          "recetas": []
        }
      ]
    }
  ]
}